{
    "Name": "Colombia",
    "Capital": {
        "DLST": "null",
        "TD": -5,
        "Flg": 2,
        "Name": "Bogota",
        "GeoPt": [
            4.36,
            -74.05
        ]
    },
    "GeoRectangle": {
        "West": -81.7281188965,
        "East": -66.8698272705,
        "North": 13.3805036545,
        "South": -4.22586965561
    },
    "SeqID": 48,
    "GeoPt": [
        4,
        -72
    ],
    "TelPref": "57",
    "CountryCodes": {
        "tld": "co",
        "iso3": "COL",
        "iso2": "CO",
        "fips": "CO",
        "isoN": 170
    },
    "states": [
        " Amazonas",
        " Antioquia",
        " Arauca",
        " Atlantico",
        " Bogota*",
        " Bolivar",
        " Boyaca",
        " Caldas",
        " Caqueta",
        " Casanare",
        " Cauca",
        " Cesar",
        " Choco",
        " Cordoba",
        " Cundinamarca",
        " Guainia",
        " Guaviare",
        " Huila",
        " La Guajira",
        " Magdalena",
        " Meta",
        " Narino",
        " Norte de Santander",
        " Putumayo",
        " Quindio",
        " Risaralda",
        " Archipielago de San Andres",
        " Providencia y Santa Catalina (colloquially San Andres y Providencia)",
        " Santander",
        " Sucre",
        " Tolima",
        " Valle del Cauca",
        " Vaupes",
        " Vichada"
    ]
}